prevampire/__init__.py
prevampire/prevampire.py
prevampire/tests/__init__.py
prevampire/tests/test_prevampire.py
prevampire-0.1.0.dist-info/LICENSE
prevampire-0.1.0.dist-info/METADATA
prevampire-0.1.0.dist-info/WHEEL
prevampire-0.1.0.dist-info/entry_points.txt
prevampire-0.1.0.dist-info/top_level.txt
prevampire-0.1.0.dist-info/RECORD
