Metadata-Version: 2.1
Name: prevampire
Version: 0.1.0
Summary: Supplementary Package to Apply to existing VAMPIRE package pipeline.
Home-page: https://github.com/onoderamia/prevampire
Author: Mia Onodera
Author-email: mconodera@gmail.com
License-File: LICENSE
Requires-Dist: numpy
Requires-Dist: matplotlib
Requires-Dist: scikit-image
Requires-Dist: vampire
Requires-Dist: skan
Requires-Dist: pandas
Requires-Dist: scipy
